agit/config.py
agit/logger.py
agit/main.py
agit/openai_api.py
agit/os_iface.py
agit/security.py
agit/selfdocument.py
agit/util.py
microagi-0.0.4.dist-info/LICENSE.txt
microagi-0.0.4.dist-info/METADATA
microagi-0.0.4.dist-info/WHEEL
microagi-0.0.4.dist-info/entry_points.txt
microagi-0.0.4.dist-info/RECORD
