Metadata-Version: 2.1
Name: microagi
Version: 0.0.4
Summary: Predictable, secure and precision tuned command-line assistant that translates natural language into Git commands.
Home-page: https://github.com/microagi
Keywords: agi,microagi,git,assistant,agent,AI,GPT
Author: Sivan Grünberg
Author-email: sivan@vitakka.co
Requires-Python: >=3.11,<4.0
Classifier: Programming Language :: Python :: 3
Classifier: Programming Language :: Python :: 3.11
Requires-Dist: autopage (>=0.5.1,<0.6.0)
Requires-Dist: colorama (>=0.4.6,<0.5.0)
Requires-Dist: openai (>=0.27.8,<0.28.0)
Requires-Dist: pydantic (>=2.0.3,<3.0.0)
Requires-Dist: pyparsing (>=3.1.1,<4.0.0)
Requires-Dist: python-dotenv (>=1.0.0,<2.0.0)
Requires-Dist: requests (>=2.31.0,<3.0.0)
